tpmmld/__init__.py
tpmmld/__main__.py
tpmmld/application.py
tpmmld/static.py
tpmmld/version.py
tpmmld-2.1.1.dist-info/METADATA
tpmmld-2.1.1.dist-info/WHEEL
tpmmld-2.1.1.dist-info/entry_points.txt
tpmmld-2.1.1.dist-info/top_level.txt
tpmmld-2.1.1.dist-info/RECORD
