Metadata-Version: 2.1
Name: tpmmld
Version: 2.1.1
Summary: ThinkPad mute-mic light daemon
Home-page: https://github.com/rubin55/tpmmld
Author: Rubin Simons
Author-email: me@rubin55.org
License: GPLv3
Requires-Dist: evdev (>=1.6.0)
Requires-Dist: pulsectl (>=22.3.2)
Requires-Dist: python-daemon (>=2.3.0)
Requires-Dist: python-dateutil (>=2.8.1)
